wabt/__init__.py
wabt/github.py
wabt/wabt.py
wabt-0.1.2.dist-info/METADATA
wabt-0.1.2.dist-info/WHEEL
wabt-0.1.2.dist-info/top_level.txt
wabt-0.1.2.dist-info/RECORD
