Metadata-Version: 2.2
Name: wabt
Version: 0.1.2
Summary: A Python wrapper for the WebAssembly Binary Toolkit (WABT)
Home-page: https://github.com/c7a2d9e/wabt.py
Author: c7a2d9e (dropout)
Author-email: c7a2d9e@sys32.dev
Classifier: Programming Language :: Python :: 3
Classifier: License :: OSI Approved :: MIT License
Classifier: Operating System :: OS Independent
Requires-Python: >=3.6
Requires-Dist: requests>=2.32.3
Requires-Dist: appdirs>=1.4.4
Dynamic: author
Dynamic: author-email
Dynamic: classifier
Dynamic: description
Dynamic: description-content-type
Dynamic: home-page
Dynamic: requires-dist
Dynamic: requires-python
Dynamic: summary
